mgpro/__init__.py
mgpro/client.py
mgpro/expand.py
mgpro/mgpro.py
mgpro/proj.py
mgpro-0.1.18.dist-info/METADATA
mgpro-0.1.18.dist-info/WHEEL
mgpro-0.1.18.dist-info/entry_points.txt
mgpro-0.1.18.dist-info/top_level.txt
mgpro-0.1.18.dist-info/RECORD
