Metadata-Version: 2.1
Name: mgpro
Version: 0.1.18
Summary: A Python Interactive command line toolbox for processing geomagnetic and gravity data
Home-page: https://github.com/xumi1993/MGPro
Author: Mijian Xu
Author-email: gomijianxu@gmail.com
License: GPLv3
Platform: UNKNOWN
Requires-Dist: pyproj
Requires-Dist: numpy
Requires-Dist: scipy
Requires-Dist: matplotlib
